kuhl_haus/magpie/__init__.py
kuhl_haus/magpie/api.py
kuhl_haus/magpie/canary/__init__.py
kuhl_haus/magpie/canary/env.py
kuhl_haus/magpie/canary/tasks/__init__.py
kuhl_haus/magpie/canary/tasks/dns_check.py
kuhl_haus/magpie/canary/tasks/http_health_check.py
kuhl_haus/magpie/canary/tasks/tls.py
kuhl_haus/magpie/canary_tasks/__init__.py
kuhl_haus/magpie/canary_tasks/tasks.py
kuhl_haus/magpie/database/__init__.py
kuhl_haus/magpie/database/apps.py
kuhl_haus/magpie/database/management/__init__.py
kuhl_haus/magpie/database/management/commands/__init__.py
kuhl_haus/magpie/database/management/commands/bootstrap.py
kuhl_haus/magpie/database/migrations/__init__.py
kuhl_haus/magpie/database/tests.py
kuhl_haus/magpie/endpoints/__init__.py
kuhl_haus/magpie/endpoints/admin.py
kuhl_haus/magpie/endpoints/api_views.py
kuhl_haus/magpie/endpoints/apps.py
kuhl_haus/magpie/endpoints/migrations/0001_initial.py
kuhl_haus/magpie/endpoints/migrations/__init__.py
kuhl_haus/magpie/endpoints/models.py
kuhl_haus/magpie/endpoints/serializers.py
kuhl_haus/magpie/endpoints/urls.py
kuhl_haus/magpie/manage.py
kuhl_haus/magpie/metrics/__init__.py
kuhl_haus/magpie/metrics/clients/__init__.py
kuhl_haus/magpie/metrics/clients/carbon_poster.py
kuhl_haus/magpie/metrics/data/__init__.py
kuhl_haus/magpie/metrics/data/metrics.py
kuhl_haus/magpie/metrics/env.py
kuhl_haus/magpie/metrics/factories/__init__.py
kuhl_haus/magpie/metrics/factories/logs.py
kuhl_haus/magpie/metrics/models/__init__.py
kuhl_haus/magpie/metrics/models/carbon_config.py
kuhl_haus/magpie/templates/base.html
kuhl_haus/magpie/templates/index.html
kuhl_haus/magpie/web/__init__.py
kuhl_haus/magpie/web/asgi.py
kuhl_haus/magpie/web/celery_app.py
kuhl_haus/magpie/web/context_processors.py
kuhl_haus/magpie/web/health.py
kuhl_haus/magpie/web/settings.py
kuhl_haus/magpie/web/urls.py
kuhl_haus/magpie/web/wsgi.py
kuhl_haus_magpie-0.5.2.dist-info/METADATA
kuhl_haus_magpie-0.5.2.dist-info/WHEEL
kuhl_haus_magpie-0.5.2.dist-info/entry_points.txt
kuhl_haus_magpie-0.5.2.dist-info/licenses/LICENSE.txt
kuhl_haus_magpie-0.5.2.dist-info/RECORD
