Metadata-Version: 2.1
Name: kuhl-haus-magpie
Version: 0.5.2
Summary: Site monitoring and synthetic transaction service
Author-Email: Tom Pounders <git@oldschool.engineer>
License: The MIT License (MIT)
Classifier: Development Status :: 4 - Beta
Classifier: Programming Language :: Python
Project-URL: Homepage, https://github.com/kuhl-haus/kuhl-haus-magpie
Project-URL: Documentation, https://github.com/kuhl-haus/kuhl-haus-magpie/wiki
Project-URL: Source, https://github.com/kuhl-haus/kuhl-haus-magpie.git
Project-URL: Changelog, https://github.com/kuhl-haus/kuhl-haus-magpie/commits
Project-URL: Tracker, https://github.com/kuhl-haus/kuhl-haus-magpie/issues
Requires-Python: >=3.12
Requires-Dist: celery
Requires-Dist: Django
Requires-Dist: djangorestframework
Requires-Dist: django-celery-beat
Requires-Dist: django-celery-results
Requires-Dist: django-cors-headers
Requires-Dist: requests
Requires-Dist: dataclasses-json
Requires-Dist: dnspython
Requires-Dist: drf-yasg
Requires-Dist: gunicorn
Requires-Dist: importlib-metadata
Requires-Dist: psycopg2-binary
Requires-Dist: psutil
Requires-Dist: pyOpenSSL
Requires-Dist: python-dotenv
Requires-Dist: uvicorn
Requires-Dist: uvicorn-worker
Provides-Extra: testing
Requires-Dist: setuptools; extra == "testing"
Requires-Dist: pdm-backend; extra == "testing"
Requires-Dist: pytest; extra == "testing"
Requires-Dist: pytest-cov; extra == "testing"
